setup.py
platonic_solids_GGM/__init__.py
platonic_solids_GGM/duality.py
platonic_solids_GGM/measures.py
platonic_solids_GGM/parts.py
platonic_solids_GGM/radius.py
platonic_solids_GGM.egg-info/PKG-INFO
platonic_solids_GGM.egg-info/SOURCES.txt
platonic_solids_GGM.egg-info/dependency_links.txt
platonic_solids_GGM.egg-info/not-zip-safe
platonic_solids_GGM.egg-info/top_level.txt