Metadata-Version: 2.1
Name: platonic-solids-GGM
Version: 0.0
Summary: Sólidos Platónicos de Gonzalo
Author-email: gonzagil.ucm@gmail.com
License: UNKNOWN
Platform: UNKNOWN
